check_jsonschema/__init__.py
check_jsonschema/__main__.py
check_jsonschema/cachedownloader.py
check_jsonschema/catalog.py
check_jsonschema/checker.py
check_jsonschema/format_errors.py
check_jsonschema/identify_filetype.py
check_jsonschema/instance_loader.py
check_jsonschema/regex_variants.py
check_jsonschema/reporter.py
check_jsonschema/result.py
check_jsonschema/utils.py
check_jsonschema/builtin_schemas/__init__.py
check_jsonschema/builtin_schemas/custom/__init__.py
check_jsonschema/builtin_schemas/custom/github-workflows-require-timeout.json
check_jsonschema/builtin_schemas/vendor/README.md
check_jsonschema/builtin_schemas/vendor/__init__.py
check_jsonschema/builtin_schemas/vendor/azure-pipelines.json
check_jsonschema/builtin_schemas/vendor/bamboo-spec.json
check_jsonschema/builtin_schemas/vendor/bitbucket-pipelines.json
check_jsonschema/builtin_schemas/vendor/buildkite.json
check_jsonschema/builtin_schemas/vendor/circle-ci.json
check_jsonschema/builtin_schemas/vendor/citation-file-format.json
check_jsonschema/builtin_schemas/vendor/cloudbuild.json
check_jsonschema/builtin_schemas/vendor/codecov.json
check_jsonschema/builtin_schemas/vendor/compose-spec.json
check_jsonschema/builtin_schemas/vendor/dependabot.json
check_jsonschema/builtin_schemas/vendor/drone-ci.json
check_jsonschema/builtin_schemas/vendor/github-actions.json
check_jsonschema/builtin_schemas/vendor/github-discussion.json
check_jsonschema/builtin_schemas/vendor/github-issue-config.json
check_jsonschema/builtin_schemas/vendor/github-issue-forms.json
check_jsonschema/builtin_schemas/vendor/github-workflows.json
check_jsonschema/builtin_schemas/vendor/gitlab-ci.json
check_jsonschema/builtin_schemas/vendor/meltano.json
check_jsonschema/builtin_schemas/vendor/mergify.json
check_jsonschema/builtin_schemas/vendor/readthedocs.json
check_jsonschema/builtin_schemas/vendor/renovate.json
check_jsonschema/builtin_schemas/vendor/snapcraft.json
check_jsonschema/builtin_schemas/vendor/taskfile.json
check_jsonschema-0.36.1.dist-info/licenses/LICENSE
check_jsonschema-0.36.1.dist-info/METADATA
check_jsonschema-0.36.1.dist-info/WHEEL
check_jsonschema-0.36.1.dist-info/entry_points.txt
check_jsonschema-0.36.1.dist-info/top_level.txt
check_jsonschema-0.36.1.dist-info/RECORD
