Metadata-Version: 2.4
Name: check-jsonschema
Version: 0.36.1
Summary: A jsonschema CLI and pre-commit hook
Author-email: Stephen Rosen <sirosen0@gmail.com>
Project-URL: Homepage, https://github.com/python-jsonschema/check-jsonschema
Classifier: Development Status :: 4 - Beta
Classifier: Intended Audience :: Developers
Classifier: License :: OSI Approved :: Apache Software License
Classifier: Programming Language :: Python :: 3
Requires-Python: >=3.9
License-File: LICENSE
Requires-Dist: tomli>=2.0; python_version < "3.11"
Requires-Dist: ruamel.yaml<0.20.0,>=0.18.10
Requires-Dist: jsonschema<5.0,>=4.18.0
Requires-Dist: regress>=2024.11.1
Requires-Dist: requests<3.0
Requires-Dist: click<9,>=8
Dynamic: license-file
